{
  "id": "d8c57c4e-bf6f-4e32-a2bf-8643532de77b",
  "queryName": "High Google KMS Crypto Key Rotation Period",
  "severity": "MEDIUM",
  "category": "Secret Management",
  "descriptionText": "KMS encryption keys should be rotated every 90 days or less. A short lifetime of encryption keys reduces the potential blast radius in case of compromise.",
  "descriptionUrl": "https://registry.terraform.io/providers/hashicorp/google/latest/docs/resources/kms_crypto_key",
  "platform": "Terraform",
  "descriptionID": "d43302d0",
  "cloudProvider": "gcp",
  "cwe": "326"
}