{
  "id": "6b2739db-9c49-4db7-b980-7816e0c248c1",
  "queryName": "API Gateway Endpoint Config is Not Private",
  "severity": "MEDIUM",
  "category": "Networking and Firewall",
  "descriptionText": "The API Endpoint type in API Gateway should be set to PRIVATE so it's not exposed to the public internet",
  "descriptionUrl": "https://registry.terraform.io/providers/hashicorp/aws/latest/docs/resources/api_gateway_rest_api",
  "platform": "Terraform",
  "descriptionID": "baf9a6d6",
  "cloudProvider": "aws",
  "cwe": "285"
}