{
  "id": "d39761d7-94ab-45b0-ab5e-27c44e381d58",
  "queryName": "Stack Notifications Disabled",
  "severity": "LOW",
  "category": "Observability",
  "descriptionText": "AWS CloudFormation should have stack notifications enabled to be notified when an event occurs",
  "descriptionUrl": "https://docs.ansible.com/ansible/latest/collections/amazon/aws/cloudformation_module.html#parameter-notification_arns",
  "platform": "Ansible",
  "descriptionID": "59f8905d",
  "cloudProvider": "aws",
  "cwe": "778",
  "oldSeverity": "MEDIUM"
}